dieselhaze/__init__.py
dieselhaze/db_util.py
dieselhaze/files.py
dieselhaze/threads.py
dieselhaze-0.3.1.data/data/LICENSE
dieselhaze-0.3.1.data/data/README.md
dieselhaze-0.3.1.dist-info/METADATA
dieselhaze-0.3.1.dist-info/RECORD
dieselhaze-0.3.1.dist-info/WHEEL
dieselhaze-0.3.1.dist-info/top_level.txt
