Metadata-Version: 2.1
Name: dieselhaze
Version: 0.3.1
Summary: Magic utility library
Home-page: https://github.com/krisfris/dieselhaze
Author: Kris
Author-email: 31852063+krisfris@users.noreply.github.com
License: MIT
Platform: UNKNOWN
Requires-Dist: pandas
